PySiglent_SSA3000x/PySiglent_SSA3000x.py
PySiglent_SSA3000x/__init__.py
PySiglent_SSA3000x-0.8.dist-info/LICENSE
PySiglent_SSA3000x-0.8.dist-info/METADATA
PySiglent_SSA3000x-0.8.dist-info/WHEEL
PySiglent_SSA3000x-0.8.dist-info/top_level.txt
PySiglent_SSA3000x-0.8.dist-info/RECORD
